run_server.py
alerts/__init__.py
alerts/handlers.py
alerts/manager.py
config/__init__.py
config/config.py
core/__init__.py
core/enums.py
core/exceptions.py
core/models.py
exporters/__init__.py
exporters/base.py
exporters/factory.py
exporters/json_exporter.py
exporters/websocket_exporter.py
monitoring_websocket_server-1.0.83.87.dist-info/licenses/LICENSE
monitors/__init__.py
monitors/base.py
monitors/disk.py
monitors/factory.py
monitors/gpu.py
monitors/memory.py
monitors/processor.py
monitors/service_memory.py
monitors/system.py
services/__init__.py
services/realtime.py
services/threadsafe.py
services/websocket_server.py
utils/__init__.py
utils/display.py
utils/formatters.py
utils/system.py
monitoring_websocket_server-1.0.83.87.dist-info/METADATA
monitoring_websocket_server-1.0.83.87.dist-info/WHEEL
monitoring_websocket_server-1.0.83.87.dist-info/entry_points.txt
monitoring_websocket_server-1.0.83.87.dist-info/top_level.txt
monitoring_websocket_server-1.0.83.87.dist-info/RECORD
