Metadata-Version: 2.4
Name: monitoring-websocket-server
Version: 1.0.83.87
Summary: Real-Time WebSocket Monitoring System
Author-email: NMicInvest <accueil@nmicinvest.com>
License-Expression: GPL-3.0-or-later
Project-URL: Homepage, https://github.com/Nmicinvest/monitoring-websocket-server/
Project-URL: Repository, https://github.com/Nmicinvest/monitoring-websocket-server/
Project-URL: Bug Tracker, https://github.com/Nmicinvest/monitoring-websocket-server/issues
Classifier: Development Status :: 5 - Production/Stable
Classifier: Intended Audience :: Developers
Classifier: Topic :: System :: Monitoring
Classifier: Programming Language :: Python :: 3
Classifier: Programming Language :: Python :: 3.8
Classifier: Programming Language :: Python :: 3.9
Classifier: Programming Language :: Python :: 3.10
Classifier: Programming Language :: Python :: 3.11
Classifier: Programming Language :: Python :: 3.12
Requires-Python: >=3.8
License-File: LICENSE
Requires-Dist: websockets
Requires-Dist: psutil
Requires-Dist: pyyaml
Requires-Dist: colorama
Requires-Dist: GPUtil
Requires-Dist: nvidia-ml-py3
Requires-Dist: pynvml
Dynamic: license-file
